trood/__init__.py
trood/cli/__init__.py
trood/cli/spaces.py
trood/cli/trood.py
trood/cli/utils.py
trood_cli-0.2.dist-info/METADATA
trood_cli-0.2.dist-info/WHEEL
trood_cli-0.2.dist-info/entry_points.txt
trood_cli-0.2.dist-info/top_level.txt
trood_cli-0.2.dist-info/RECORD
