Metadata-Version: 2.1
Name: trood-cli
Version: 0.2
Summary: UNKNOWN
Home-page: UNKNOWN
Author: Trood Inc
Author-email: UNKNOWN
License: UNKNOWN
Platform: UNKNOWN
Requires-Dist: requests (==2.22.0)
Requires-Dist: click
Requires-Dist: pyfiglet
Requires-Dist: tabulate
Requires-Dist: keyring
